teensypower/__init__.py
teensypower/_version.py
teensypower/teensypower.py
teensypower-0.0.2.dist-info/METADATA
teensypower-0.0.2.dist-info/WHEEL
teensypower-0.0.2.dist-info/top_level.txt
teensypower-0.0.2.dist-info/RECORD
