Metadata-Version: 2.1
Name: teensypower
Version: 0.0.2
Summary: teensy controlled power switch
Home-page: UNKNOWN
Author: Jaehee Park
Author-email: jaehee@ramonaoptics.com
License: UNKNOWN
Platform: UNKNOWN
Requires-Python: >=3.6
Requires-Dist: teensytoany
